runestone/__init__.py
runestone/__main__.py
runestone/unittest_base.py
runestone/__pycache__/__init__.cpython-39.pyc
runestone/accessibility/__init__.py
runestone/accessibility/accessibility.py
runestone/accessibility/__pycache__/__init__.cpython-39.pyc
runestone/accessibility/__pycache__/accessibility.cpython-39.pyc
runestone/accessibility/css/accessibility.css
runestone/accessibility/css/accessibilitydarkest.css
runestone/accessibility/css/accessibilitylight.css
runestone/activecode/README.md
runestone/activecode/__init__.py
runestone/activecode/actest.html
runestone/activecode/activecode.py
runestone/activecode/petljapg.py
runestone/activecode/textfield.py
runestone/activecode/__pycache__/__init__.cpython-39.pyc
runestone/activecode/__pycache__/activecode.cpython-39.pyc
runestone/activecode/__pycache__/textfield.cpython-39.pyc
runestone/activecode/css/activecode.css
runestone/activecode/js/activecode-i18n.en.js
runestone/activecode/js/activecode-i18n.hu.js
runestone/activecode/js/activecode-i18n.sr-Cyrl.js
runestone/activecode/js/activecode-i18n.sr-Latn.js
runestone/activecode/js/activecode-i18n.sr.js
runestone/activecode/js/activecode.js
runestone/activecode/js/sharedb.js
runestone/activecode/js/timed_activecode.js
runestone/animation/README.rst
runestone/animation/__init__.py
runestone/animation/animation.py
runestone/animation/animationrefactor.html
runestone/animation/animationrefactor.js
runestone/animation/chart.html
runestone/animation/searchmodels.js
runestone/animation/simpletree.html
runestone/animation/simpletree.js
runestone/animation/sortingbase.html
runestone/animation/sortingdemo.html
runestone/animation/sortingdemo.js
runestone/animation/sortingpackage.html
runestone/animation/sortingpackage.js
runestone/animation/__pycache__/__init__.cpython-39.pyc
runestone/animation/__pycache__/animation.cpython-39.pyc
runestone/animation/jqchart/gChartBasic.html
runestone/animation/jqchart/jquery.gchart.ext.js
runestone_petljadoc-3.1.2.8.dist-info/licenses/LICENSE.txt
runestone_petljadoc-3.1.2.8.dist-info/METADATA
runestone_petljadoc-3.1.2.8.dist-info/WHEEL
runestone_petljadoc-3.1.2.8.dist-info/entry_points.txt
runestone_petljadoc-3.1.2.8.dist-info/top_level.txt
runestone_petljadoc-3.1.2.8.dist-info/RECORD
