Metadata-Version: 2.4
Name: runestone-petljadoc
Version: 3.1.2.8
Summary: Sphinx extensions for writing interactive documents.
Home-page: https://github.com/RunestoneInteractive/RunestoneComponents
Download-URL: https://github.com/RunestoneInteractive/RunestoneComponents/tarball/3.1.1
Author: Brad Miller
Author-email: bonelake@mac.com
License: GPL
Keywords: runestone,sphinx,ebook
Classifier: Development Status :: 5 - Production/Stable
Classifier: Environment :: Console
Classifier: Environment :: Plugins
Classifier: Environment :: Web Environment
Classifier: Framework :: Sphinx :: Extension
Classifier: Intended Audience :: Education
Classifier: License :: OSI Approved :: GNU General Public License v3 or later (GPLv3+)
Classifier: Operating System :: MacOS
Classifier: Operating System :: Unix
Classifier: Programming Language :: Python
Classifier: Programming Language :: Python :: 2.7
Classifier: Programming Language :: Python :: 3.6
Classifier: Topic :: Education
Classifier: Topic :: Text Processing :: Markup
License-File: LICENSE.txt
Requires-Dist: click
Requires-Dist: Paver>=1.2.4
Requires-Dist: six
Requires-Dist: Sphinx>=1.7.1
Requires-Dist: sphinxcontrib-paverutils>=1.17
Requires-Dist: cogapp>=2.5
Requires-Dist: SQLAlchemy>=1.0.13
Requires-Dist: selenium>=2.53.6
Requires-Dist: pyvirtualdisplay
Dynamic: author
Dynamic: author-email
Dynamic: classifier
Dynamic: description
Dynamic: download-url
Dynamic: home-page
Dynamic: keywords
Dynamic: license
Dynamic: license-file
Dynamic: requires-dist
Dynamic: summary
